LICENSE
MANIFEST.in
README.rst
setup.py
ascetic/__init__.py
ascetic/exceptions.py
ascetic/fields.py
ascetic/identity_maps.py
ascetic/interfaces.py
ascetic/mappers.py
ascetic/models.py
ascetic/observable.py
ascetic/query.py
ascetic/relations.py
ascetic/settings.py
ascetic/signals.py
ascetic/transaction.py
ascetic/utils.py
ascetic/validators.py
ascetic.egg-info/PKG-INFO
ascetic.egg-info/SOURCES.txt
ascetic.egg-info/dependency_links.txt
ascetic.egg-info/requires.txt
ascetic.egg-info/top_level.txt
ascetic/contrib/__init__.py
ascetic/contrib/gfk.py
ascetic/contrib/modeltranslation.py
ascetic/contrib/multilingual.py
ascetic/contrib/polymorphic.py
ascetic/contrib/tree.py
ascetic/contrib/versioning.py
ascetic/contrib/tests/__init__.py
ascetic/contrib/tests/test_gfk.py
ascetic/contrib/tests/test_modeltranslation.py
ascetic/contrib/tests/test_polymorphic.py
ascetic/contrib/tests/test_tree.py
ascetic/databases/__init__.py
ascetic/databases/base.py
ascetic/databases/mysql.py
ascetic/databases/postgresql.py
ascetic/databases/sqlite.py
ascetic/tests/__init__.py
ascetic/tests/test_mappers.py
ascetic/tests/test_relations.py
ascetic/tests/test_utils.py
ascetic/tests/test_validators.py