Metadata-Version: 1.1
Name: ascetic
Version: 0.7.2.40
Summary: Lightweight python datamapper ORM (Object-relational mapper).
Home-page: https://bitbucket.org/emacsway/ascetic
Author: Ivan Zakrevsky
Author-email: ivzak@yandex.ru
License: MIT License
Keywords: ORM Database DataMapper SQL
Platform: UNKNOWN
Classifier: Development Status :: 1 - Planning
Classifier: Intended Audience :: Developers
Classifier: License :: OSI Approved :: MIT License
Classifier: Operating System :: OS Independent
Classifier: Programming Language :: Python
Classifier: Programming Language :: Python :: 2
Classifier: Programming Language :: Python :: 2.7
Classifier: Programming Language :: Python :: 3
Classifier: Programming Language :: Python :: 3.2
Classifier: Programming Language :: Python :: 3.3
Classifier: Programming Language :: Python :: 3.4
Classifier: Topic :: Software Development :: Libraries :: Python Modules
